<?xml version="1.0" encoding="utf-8"?>
<VisualState xmlns:xsi="http://www.w3.org/2001/XMLSchema-instance" xmlns:xsd="http://www.w3.org/2001/XMLSchema" ShowCheckBoxes="false">
  <TopNode>[0-1000]C:\Development\Samples\Automation Testing\WebDriverTest\WebDriverTest.nunit</TopNode>
  <SelectedNode>[0-1033]C:\Development\Samples\Automation Testing\WebDriverTest\WebDriver.Extensions.Tests\bin\Debug\WebDriver.Extensions.Tests.dll</SelectedNode>
  <ExcludeCategories>false</ExcludeCategories>
  <Nodes>
    <Node UniqueName="[0-1000]C:\Development\Samples\Automation Testing\WebDriverTest\WebDriverTest.nunit" Expanded="true" />
    <Node UniqueName="[0-1033]C:\Development\Samples\Automation Testing\WebDriverTest\WebDriver.Extensions.Tests\bin\Debug\WebDriver.Extensions.Tests.dll" Expanded="true" />
    <Node UniqueName="[0-1034]WebDriver" Expanded="true" />
    <Node UniqueName="[0-1035]WebDriver.Extensions" Expanded="true" />
    <Node UniqueName="[0-1036]WebDriver.Extensions.Tests" Expanded="true" />
    <Node UniqueName="[0-1001]WebDriver.Extensions.Tests.WebDriverToolsTests" Expanded="true" />
    <Node UniqueName="[0-1054]WebDriver" Expanded="true" />
    <Node UniqueName="[0-1055]WebDriver.Google" Expanded="true" />
    <Node UniqueName="[0-1056]WebDriver.Google.Search" Expanded="true" />
    <Node UniqueName="[0-1057]WebDriver.Google.Search.UITests" Expanded="true" />
    <Node UniqueName="[0-1037]WebDriver.Google.Search.UITests.SearchTests" Expanded="true" />
    <Node UniqueName="[0-1038]WebDriver.Google.Search.UITests.SearchTests.TestThatICanSearchForSomething" Expanded="true" />
    <Node UniqueName="[0-1039]WebDriver.Google.Search.UITests.SearchTests.TestThatICanSearchForSomething" Expanded="true" />
    <Node UniqueName="[0-1049]WebDriver.Google.Search.UITests.SearchTests.TestThatICanSearchForSomething" Expanded="true" />
  </Nodes>
</VisualState>